setup.py
PyCalculator/__init__.py
PyCalculator/baseCalculator.py
PyCalculator/calculator.py
PyCalculator/eqInput.py
PyCalculator/postfixCalc.py
PyCalculator/rpn.py
PyCalculator/tests.py
PyCalculator/window.py
pycalculator.egg-info/PKG-INFO
pycalculator.egg-info/SOURCES.txt
pycalculator.egg-info/dependency_links.txt
pycalculator.egg-info/not-zip-safe
pycalculator.egg-info/top_level.txt